cleantext/__init__.py
cleantext/clean.py
cleantext/constants.py
cleantext/specials.py
clean_text-0.2.0.dist-info/LICENSE
clean_text-0.2.0.dist-info/WHEEL
clean_text-0.2.0.dist-info/METADATA
clean_text-0.2.0.dist-info/RECORD
